MANIFEST.in
README.rst
requirements.txt
setup.cfg
setup.py
pydhcpdparser/__init__.py
pydhcpdparser/dhcp_conf_parser.py
pydhcpdparser/test_dhcp_conf_parser.py
pydhcpdparser.egg-info/PKG-INFO
pydhcpdparser.egg-info/SOURCES.txt
pydhcpdparser.egg-info/dependency_links.txt
pydhcpdparser.egg-info/requires.txt
pydhcpdparser.egg-info/top_level.txt
pydhcpdparser/test_files/__init__.py
pydhcpdparser/test_files/dhcpd_conf_data.py
pydhcpdparser/test_files/dhcpd_global_stmt_data.py
pydhcpdparser/test_files/dhcpd_host_stmt_data.py
pydhcpdparser/test_files/dhcpd_subnets_conf_data.py
pydhcpdparser/test_files/dhcpd_zone_conf.json